SuperRPA/__init__.py
SuperRPA/Super_PyPackage/__init__.py
SuperRPA/Super_PyPackage/py_selenium.py
SuperRPA/Super_PyPackage/file_text/__init__.py
SuperRPA/Super_PyPackage/file_text/py_csv.py
SuperRPA/Super_PyPackage/file_text/py_excel.py
SuperRPA/Super_PyPackage/file_text/py_files.py
SuperRPA/Super_PyPackage/file_text/py_txt.py
SuperRPA/Super_PyPackage/py_automation/__init__.py
SuperRPA/Super_PyPackage/py_automation/keyboard.py
SuperRPA/Super_PyPackage/py_selenium/__init__.py
SuperRPA/Super_PyPackage/py_selenium/py_selenium.py
Super_PyPackage/__init__.py
Super_PyPackage/py_selenium.py
SuperRPA-0.0.9.dist-info/LICENSE.txt
SuperRPA-0.0.9.dist-info/METADATA
SuperRPA-0.0.9.dist-info/WHEEL
SuperRPA-0.0.9.dist-info/top_level.txt
SuperRPA-0.0.9.dist-info/RECORD
