Metadata-Version: 2.1
Name: SuperRPA
Version: 0.0.9
Summary: 二次封装 Selenium，并且后期会维护搭载各种文本、csv、xlsx、本地文件等操作。
Home-page: https://gitee.com/xiaoye_01/super-rpa
Author: 叶狼
Author-email: yelang97@qq.com
License: UNKNOWN
Platform: UNKNOWN
Classifier: Programming Language :: Python :: 3
Classifier: License :: OSI Approved :: MIT License
Classifier: Operating System :: OS Independent
